fastbackup/__init__.py
fastbackup/cli.py
fastbackup/core.py
fastbackup-1.0.3.dist-info/METADATA
fastbackup-1.0.3.dist-info/WHEEL
fastbackup-1.0.3.dist-info/entry_points.txt
fastbackup-1.0.3.dist-info/top_level.txt
fastbackup-1.0.3.dist-info/RECORD
