Metadata-Version: 2.4
Name: fastbackup
Version: 1.0.3
Summary: 一行导入式Python项目实验备份工具
Home-page: https://github.com/chenziwenhaoshuai/fastbackup
Author: ZiwenChen
Author-email: chenziwen <1304005976@qq.com>
License: MIT
Project-URL: Homepage, https://github.com/chenziwenhaoshuai/fastbackup
Project-URL: Repository, https://github.com/chenziwenhaoshuai/fastbackup.git
Project-URL: Issues, https://github.com/chenziwenhaoshuai/fastbackup/issues
Keywords: backup,experiment,version-control,development
Classifier: Development Status :: 5 - Production/Stable
Classifier: Intended Audience :: Developers
Classifier: License :: OSI Approved :: MIT License
Classifier: Operating System :: OS Independent
Classifier: Programming Language :: Python :: 3
Classifier: Programming Language :: Python :: 3.6
Classifier: Programming Language :: Python :: 3.7
Classifier: Programming Language :: Python :: 3.8
Classifier: Programming Language :: Python :: 3.9
Classifier: Programming Language :: Python :: 3.10
Classifier: Programming Language :: Python :: 3.11
Requires-Python: >=3.6
Dynamic: author
Dynamic: home-page
Dynamic: requires-python
